vigilant/__init__.py
vigilant/logger.py
vigilant/actions/__init__.py
vigilant/actions/assertions.py
vigilant/actions/data_saver.py
vigilant/actions/finder.py
vigilant/actions/vigilant_actions.py
vigilant/actions/vigilant_pdf.py
vigilant/actions/waiter.py
vigilant/bidi/__init__.py
vigilant/bidi/_bidi.py
vigilant/driver/__init__.py
vigilant/driver/vigilant_driver.py
vigilant_kit-1.6.0.dist-info/METADATA
vigilant_kit-1.6.0.dist-info/WHEEL
vigilant_kit-1.6.0.dist-info/licenses/LICENSE
vigilant_kit-1.6.0.dist-info/RECORD
