Metadata-Version: 2.4
Name: vigilant_kit
Version: 1.6.0
Summary: Library that makes functional testing with Selenium WebDriver fast and easy. 
Project-URL: Homepage, https://github.com/ivpel/vigilant
Project-URL: Bug Tracker, https://github.com/ivpel/vigilant/issues
Author-email: Pelykh Ivan <ivan.pelykh@protonmail.com>
License-File: LICENSE
Keywords: bdd,functional,functional-testing,pytest,selenium,tdd,testing,unittest,webdriver
Requires-Python: >=3.7
Requires-Dist: pymupdf
Requires-Dist: pyyaml
Requires-Dist: selenium
